django_pipeline_typescript_compiler-0.3.dist-info/DESCRIPTION.rst
django_pipeline_typescript_compiler-0.3.dist-info/METADATA
django_pipeline_typescript_compiler-0.3.dist-info/RECORD
django_pipeline_typescript_compiler-0.3.dist-info/WHEEL
django_pipeline_typescript_compiler-0.3.dist-info/metadata.json
django_pipeline_typescript_compiler-0.3.dist-info/top_level.txt
pipeline_typescript/__init__.py
pipeline_typescript/compilers.py
